{
  "anvils": {
    "diamond": {
      "enabled": true,
      "color": "#00FFFF",
      "durability": 32,
      "cap": 32767,
      "weight": 1,
      "enchantability": 1.1,
      "playerDamage": true
    },
    "gold": {
      "enabled": true,
      "color": "#FEE048",
      "durability": 4,
      "cap": 160,
      "weight": 2.5,
      "enchantability": 2.8,
      "playerDamage": false
    },
    "stone": {
      "enabled": true,
      "color": "#808080",
      "durability": 0,
      "cap": 20,
      "weight": 0.7,
      "enchantability": 0.5,
      "playerDamage": false
    }
  }
}